infn_ophyd_hal/__init__.py
infn_ophyd_hal/device_factory.py
infn_ophyd_hal/epik8s_device.py
infn_ophyd_hal/io_basic.py
infn_ophyd_hal/ophyd_motor.py
infn_ophyd_hal/ophyd_ps.py
infn_ophyd_hal/ophyd_ps_dantemag.py
infn_ophyd_hal/ophyd_ps_sim.py
infn_ophyd_hal/spp_ophyd_bpm.py
infn_ophyd_hal/tml_ophyd_motor.py
infn_ophyd_hal/unimag_ophyd_ps.py
infn_ophyd_hal/vac_basic.py
infn_ophyd_hal-2.12.4.dist-info/METADATA
infn_ophyd_hal-2.12.4.dist-info/WHEEL
infn_ophyd_hal-2.12.4.dist-info/top_level.txt
infn_ophyd_hal-2.12.4.dist-info/RECORD
