Metadata-Version: 2.4
Name: infn_ophyd_hal
Version: 2.12.4
Summary: Ophyd HAL for controlling motors, cameras, magnets... specifically INFN facilities
Author: Andrea Michelotti
Author-email: andrea.michelotti@infn.it
Classifier: Programming Language :: Python :: 3
Classifier: License :: OSI Approved :: MIT License
Classifier: Operating System :: OS Independent
Requires-Python: >=3.8.3
Requires-Dist: ophyd
Requires-Dist: asyncio
Requires-Dist: pyepics
Requires-Dist: pyyaml
Dynamic: author
Dynamic: author-email
Dynamic: classifier
Dynamic: requires-dist
Dynamic: requires-python
Dynamic: summary
